LFSR/rtl/LFSR.sv
// Code your design here

module LFSR(
	input clk,
  	input RSTn,
  output [3:0]lfsr_o
);
  
  logic [3:0]lfsr_ff;
  logic [3:0]nxt_lfsr;
  
  assign lfsr_o = lfsr_ff;
  
  always @(posedge clk or negedge RSTn) 
    begin
      if(!RSTn) begin
        lfsr_ff <= 4'hf;
      end
      else begin
        lfsr_ff <= nxt_lfsr;
      end
    end
  
  assign nxt_lfsr = {lfsr_ff[2:0],lfsr_ff[3]^lfsr_ff[2]};
  
endmodule

LFSR/tbench/LFSR_tb.sv
// Code your testbench here
// or browse Examples

`timescale 1ns/1ps
module LFSR_tb;
  
  logic clk;
  logic RSTn;
  logic [3:0]lfsr_o;
  
  //DUT instantiation
  LFSR I_DUT(.*);
  
  //clock generation
  always #5 clk = ~clk;
  
  initial begin
    clk = 0;
    RSTn = 1; #10;
    RSTn = 0; #10;
    RSTn = 1; #10;
    #200;
    $finish;
  end
  
  initial begin
    $monitor("lfsr_o = %b",lfsr_o);
    $dumpfile("dump.vcd"); 
    $dumpvars;
  end
  
endmodule

LFSR/iverilog/dump.vcd
$date
	Mon Oct 31 00:39:14 2022
$end
$version
	Icarus Verilog
$end
$timescale
	1ps
$end
$scope module LFSR_tb $end
$var wire 4 ! lfsr_o [3:0] $end
$var reg 1 " RSTn $end
$var reg 1 # clk $end
$scope module I_DUT $end
$var wire 1 " RSTn $end
$var wire 1 # clk $end
$var wire 4 $ lfsr_o [3:0] $end
$var wire 4 % nxt_lfsr [3:0] $end
$var reg 4 & lfsr_ff [3:0] $end
$upscope $end
$upscope $end
$enddefinitions $end
#0
$dumpvars
bx &
bx %
bx $
0#
1"
bx !
$end
#5000
1#
#10000
b1110 %
b1111 !
b1111 $
b1111 &
0#
0"
#15000
1#
#20000
0#
1"
#25000
b1100 %
b1110 !
b1110 $
b1110 &
1#
#30000
0#
#35000
b1000 %
b1100 !
b1100 $
b1100 &
1#
#40000
0#
#45000
b1 %
b1000 !
b1000 $
b1000 &
1#
#50000
0#
#55000
b10 %
b1 !
b1 $
b1 &
1#
#60000
0#
#65000
b100 %
b10 !
b10 $
b10 &
1#
#70000
0#
#75000
b1001 %
b100 !
b100 $
b100 &
1#
#80000
0#
#85000
b11 %
b1001 !
b1001 $
b1001 &
1#
#90000
0#
#95000
b110 %
b11 !
b11 $
b11 &
1#
#100000
0#
#105000
b1101 %
b110 !
b110 $
b110 &
1#
#110000
0#
#115000
b1010 %
b1101 !
b1101 $
b1101 &
1#
#120000
0#
#125000
b101 %
b1010 !
b1010 $
b1010 &
1#
#130000
0#
#135000
b1011 %
b101 !
b101 $
b101 &
1#
#140000
0#
#145000
b111 %
b1011 !
b1011 $
b1011 &
1#
#150000
0#
#155000
b1111 %
b111 !
b111 $
b111 &
1#
#160000
0#
#165000
b1110 %
b1111 !
b1111 $
b1111 &
1#
#170000
0#
#175000
b1100 %
b1110 !
b1110 $
b1110 &
1#
#180000
0#
#185000
b1000 %
b1100 !
b1100 $
b1100 &
1#
#190000
0#
#195000
b1 %
b1000 !
b1000 $
b1000 &
1#
#200000
0#
#205000
b10 %
b1 !
b1 $
b1 &
1#
#210000
0#
#215000
b100 %
b10 !
b10 $
b10 &
1#
#220000
0#
#225000
b1001 %
b100 !
b100 $
b100 &
1#
