nrzi/rtl/nrzi1.sv
module nrzi(input clk_i,input resetn_i,input data_i,output  y_o);

parameter TRUE=1,
	  FALSE=0;

logic next_state,prev_state,prev_input;

typedef enum{
	S_NOCHANGE,
	S_CHANGE
}e_state;

e_state state;
e_state e_next_state;
e_state e_prev_state;


assign y_o=prev_state;

always @(posedge clk_i or negedge resetn_i)
begin
	if(!resetn_i)
       	begin
		prev_state<=0;
		
	end
	else 
	begin
		prev_state<=next_state;
		e_prev_state<=e_next_state;
	end	
end

always @(data_i)
begin
	if(transition(data_i))
	begin
		e_next_state<=S_CHANGE;
		next_state<=~prev_state;	
	end
	else
	begin
		next_state<=prev_state;
		e_next_state<=S_NOCHANGE;
	end
end


endmodule

nrzi/tbench/tb_nrzi.sv
`timescale 1ns/1ps

module tb_nrzi();
reg count;
wire y_o;
reg resetn_i;
reg clk_i;

nrzi I_NRZI(clk_i,resetn_i,count,y_o);

//clk generation
always #10 clk_i=~clk_i;

initial begin
         clk_i = 0;
        resetn_i =1'b0;
        #20 resetn_i = 1'b1;
        #20 resetn_i = 1'b0;
        #20 resetn_i = 1'b1;
	count=1'b0;

	#1500 $finish;
end


always @(negedge clk_i)
begin
	count=count+1;
end

initial begin
	$display("Simulation Result are as follows:");
 	$monitor(" resetn_i: %b, clk: %b, a_i: %b, y_o: %b", resetn_i, clk_i, count, y_o);
end

initial begin
	 if ($test$plusargs("trace") != 0) begin
                $display("[%0t] Tracing to logs/vlt_dump.vcd...\n", $time);
                $dumpfile("logs/vlt_dump.vcd");
                $dumpvars;
        end
        $display("[%0t] Model Running...\n", $time);
end


endmodule

nrzi/iverilog/logs/vlt_dump.vcd
$date
	Wed Jun  9 18:47:45 2021
$end
$version
	Icarus Verilog
$end
$timescale
	1ps
$end
$scope module tb_nrzi $end
$var wire 1 ! y_o $end
$var reg 1 " clk_i $end
$var reg 1 # count $end
$var reg 1 $ resetn_i $end
$scope module I_NRZI $end
$var wire 1 " clk_i $end
$var wire 1 # data_i $end
$var wire 1 $ resetn_i $end
$var wire 1 ! y_o $end
$var reg 1 % next_state $end
$var reg 1 & prev_state $end
$upscope $end
$upscope $end
$enddefinitions $end
#0
$dumpvars
0&
0%
0$
x#
0"
0!
$end
#10000
1"
#20000
0"
1$
#30000
1"
#40000
0"
0$
#50000
1"
#60000
1%
0"
1#
1$
#70000
1!
1&
1"
#80000
0#
0"
#90000
1"
#100000
0%
1#
0"
#110000
0!
0&
1"
#120000
0#
0"
#130000
1"
#140000
1%
1#
0"
#150000
1!
1&
1"
#160000
0#
0"
#170000
1"
#180000
0%
1#
0"
#190000
0!
0&
1"
#200000
0#
0"
#210000
1"
#220000
1%
1#
0"
#230000
1!
1&
1"
#240000
0#
0"
#250000
1"
#260000
0%
1#
0"
#270000
0!
0&
1"
#280000
0#
0"
#290000
1"
#300000
1%
1#
0"
#310000
1!
1&
1"
#320000
0#
0"
#330000
1"
#340000
0%
1#
0"
#350000
0!
0&
1"
#360000
0#
0"
#370000
1"
#380000
1%
1#
0"
#390000
1!
1&
1"
#400000
0#
0"
#410000
1"
#420000
0%
1#
0"
#430000
0!
0&
1"
#440000
0#
0"
#450000
1"
#460000
1%
1#
0"
#470000
1!
1&
1"
#480000
0#
0"
#490000
1"
#500000
0%
1#
0"
#510000
0!
0&
1"
#520000
0#
0"
#530000
1"
#540000
1%
1#
0"
#550000
1!
1&
1"
#560000
0#
0"
#570000
1"
#580000
0%
1#
0"
#590000
0!
0&
1"
#600000
0#
0"
#610000
1"
#620000
1%
1#
0"
#630000
1!
1&
1"
#640000
0#
0"
#650000
1"
#660000
0%
1#
0"
#670000
0!
0&
1"
#680000
0#
0"
#690000
1"
#700000
1%
1#
0"
#710000
1!
1&
1"
#720000
0#
0"
#730000
1"
#740000
0%
1#
0"
#750000
0!
0&
1"
#760000
0#
0"
#770000
1"
#780000
1%
1#
0"
#790000
1!
1&
1"
#800000
0#
0"
#810000
1"
#820000
0%
1#
0"
#830000
0!
0&
1"
#840000
0#
0"
#850000
1"
#860000
1%
1#
0"
#870000
1!
1&
1"
#880000
0#
0"
#890000
1"
#900000
0%
1#
0"
#910000
0!
0&
1"
#920000
0#
0"
#930000
1"
#940000
1%
1#
0"
#950000
1!
1&
1"
#960000
0#
0"
#970000
1"
#980000
0%
1#
0"
#990000
0!
0&
1"
#1000000
0#
0"
#1010000
1"
#1020000
1%
1#
0"
#1030000
1!
1&
1"
#1040000
0#
0"
#1050000
1"
#1060000
0%
1#
0"
#1070000
0!
0&
1"
#1080000
0#
0"
#1090000
1"
#1100000
1%
1#
0"
#1110000
1!
1&
1"
#1120000
0#
0"
#1130000
1"
#1140000
0%
1#
0"
#1150000
0!
0&
1"
#1160000
0#
0"
#1170000
1"
#1180000
1%
1#
0"
#1190000
1!
1&
1"
#1200000
0#
0"
#1210000
1"
#1220000
0%
1#
0"
#1230000
0!
0&
1"
#1240000
0#
0"
#1250000
1"
#1260000
1%
1#
0"
#1270000
1!
1&
1"
#1280000
0#
0"
#1290000
1"
#1300000
0%
1#
0"
#1310000
0!
0&
1"
#1320000
0#
0"
#1330000
1"
#1340000
1%
1#
0"
#1350000
1!
1&
1"
#1360000
0#
0"
#1370000
1"
#1380000
0%
1#
0"
#1390000
0!
0&
1"
#1400000
0#
0"
#1410000
1"
#1420000
1%
1#
0"
#1430000
1!
1&
1"
#1440000
0#
0"
#1450000
1"
#1460000
0%
1#
0"
#1470000
0!
0&
1"
#1480000
0#
0"
#1490000
1"
#1500000
1%
1#
0"
#1510000
1!
1&
1"
#1520000
0#
0"
#1530000
1"
#1540000
0%
1#
0"
#1550000
0!
0&
1"
#1560000
0#
0"
